sony_automator_controls/__init__.py
sony_automator_controls/__main__.py
sony_automator_controls/core.py
sony_automator_controls/gui_launcher.py
sony_automator_controls/updater.py
sony_automator_controls-1.1.0.dist-info/METADATA
sony_automator_controls-1.1.0.dist-info/WHEEL
sony_automator_controls-1.1.0.dist-info/entry_points.txt
sony_automator_controls-1.1.0.dist-info/top_level.txt
sony_automator_controls-1.1.0.dist-info/RECORD
