Metadata-Version: 2.4
Name: sony-automator-controls
Version: 1.1.0
Summary: Sony Automator Controls - TCP to HTTP command bridge for Cuez Automator
Author-email: BlueElliott <elliott.ramdass10@gmail.com>
License: MIT
Project-URL: Homepage, https://github.com/BlueElliott/Elliotts-Sony-Automator-Controls
Project-URL: Repository, https://github.com/BlueElliott/Elliotts-Sony-Automator-Controls
Project-URL: Issues, https://github.com/BlueElliott/Elliotts-Sony-Automator-Controls/issues
Project-URL: Documentation, https://github.com/BlueElliott/Elliotts-Sony-Automator-Controls#readme
Keywords: sony,automator,tcp,http,control,broadcast,automation
Classifier: Development Status :: 4 - Beta
Classifier: Intended Audience :: Developers
Classifier: Intended Audience :: System Administrators
Classifier: License :: OSI Approved :: MIT License
Classifier: Operating System :: Microsoft :: Windows
Classifier: Operating System :: POSIX :: Linux
Classifier: Operating System :: MacOS
Classifier: Programming Language :: Python :: 3
Classifier: Programming Language :: Python :: 3.8
Classifier: Programming Language :: Python :: 3.9
Classifier: Programming Language :: Python :: 3.10
Classifier: Programming Language :: Python :: 3.11
Classifier: Programming Language :: Python :: 3.12
Classifier: Topic :: Internet :: WWW/HTTP
Classifier: Topic :: System :: Monitoring
Requires-Python: >=3.8
Requires-Dist: fastapi>=0.104.0
Requires-Dist: uvicorn[standard]>=0.24.0
Requires-Dist: pydantic>=2.0.0
Requires-Dist: requests>=2.31.0
Requires-Dist: pystray>=0.19.0
Requires-Dist: Pillow>=10.0.0
Requires-Dist: psutil>=5.9.0
Provides-Extra: dev
Requires-Dist: pytest>=7.4.0; extra == "dev"
Requires-Dist: pytest-cov>=4.1.0; extra == "dev"
Requires-Dist: pytest-asyncio>=0.21.0; extra == "dev"
Requires-Dist: black>=23.0.0; extra == "dev"
Requires-Dist: ruff>=0.1.0; extra == "dev"
Requires-Dist: bandit>=1.7.0; extra == "dev"
Provides-Extra: build
Requires-Dist: pyinstaller>=6.0.0; extra == "build"
Requires-Dist: build>=1.0.0; extra == "build"
Requires-Dist: twine>=4.0.0; extra == "build"
